wntr/__init__.py
wntr/epanet/__init__.py
wntr/epanet/exceptions.py
wntr/epanet/io.py
wntr/epanet/toolkit.py
wntr/epanet/util.py
wntr/epanet/libepanet/__init__.py
wntr/epanet/libepanet/darwin-arm/libepanet2.dylib
wntr/epanet/libepanet/darwin-arm/libepanetmsx.dylib
wntr/epanet/libepanet/darwin-formula/libomp.rb
wntr/epanet/libepanet/darwin-x64/libepanet2.dylib
wntr/epanet/libepanet/darwin-x64/libepanet20.dylib
wntr/epanet/libepanet/darwin-x64/libepanet22.dylib
wntr/epanet/libepanet/darwin-x64/libepanetmsx.dylib
wntr/epanet/libepanet/linux-x64/libepanet2.so
wntr/epanet/libepanet/linux-x64/libepanet20.so
wntr/epanet/libepanet/linux-x64/libepanet22.so
wntr/epanet/libepanet/linux-x64/libepanetmsx.so
wntr/epanet/libepanet/windows-x64/epanet2.dll
wntr/epanet/libepanet/windows-x64/epanet20.dll
wntr/epanet/libepanet/windows-x64/epanet22.dll
wntr/epanet/libepanet/windows-x64/epanetmsx.dll
wntr/epanet/msx/__init__.py
wntr/epanet/msx/enums.py
wntr/epanet/msx/exceptions.py
wntr/epanet/msx/io.py
wntr/epanet/msx/toolkit.py
wntr/gis/__init__.py
wntr/gis/geospatial.py
wntr/gis/network.py
wntr/graphics/__init__.py
wntr/graphics/color.py
wntr/graphics/curve.py
wntr/graphics/layer.py
wntr/graphics/network.py
wntr/library/msx/arsenic_chloramine.json
wntr/library/msx/batch_chloramine_decay.json
wntr/library/msx/lead_ppm.json
wntr/library/msx/nicotine.json
wntr/library/msx/nicotine_ri.json
wntr/metrics/__init__.py
wntr/metrics/economic.py
wntr/metrics/hydraulic.py
wntr/metrics/misc.py
wntr/metrics/topographic.py
wntr/metrics/water_security.py
wntr/morph/__init__.py
wntr/morph/link.py
wntr/morph/node.py
wntr/morph/skel.py
wntr/msx/__init__.py
wntr/msx/base.py
wntr/msx/elements.py
wntr/msx/io.py
wntr/msx/model.py
wntr/msx/options.py
wntr/network/__init__.py
wntr/network/base.py
wntr/network/controls.py
wntr/network/elements.py
wntr/network/io.py
wntr/network/layer.py
wntr/network/model.py
wntr/network/options.py
wntr/scenario/__init__.py
wntr/scenario/earthquake.py
wntr-1.3.2.dist-info/LICENSE.md
wntr-1.3.2.dist-info/METADATA
wntr-1.3.2.dist-info/WHEEL
wntr-1.3.2.dist-info/top_level.txt
wntr-1.3.2.dist-info/RECORD
