Metadata-Version: 2.2
Name: wntr
Version: 1.3.2
Summary: Water Network Tool for Resilience
Home-page: https://github.com/USEPA/WNTR
Author: WNTR Developers
Maintainer-email: kaklise@sandia.gov
License: Revised BSD
License-File: LICENSE.md
Requires-Dist: numpy<2.0,>=1.21
Requires-Dist: scipy
Requires-Dist: networkx
Requires-Dist: pandas
Requires-Dist: matplotlib
Requires-Dist: setuptools
Dynamic: author
Dynamic: description
Dynamic: home-page
Dynamic: license
Dynamic: maintainer-email
Dynamic: requires-dist
Dynamic: summary
